secdata/__init__.py
secdata-0.0.2.3.dist-info/LICENSE
secdata-0.0.2.3.dist-info/METADATA
secdata-0.0.2.3.dist-info/WHEEL
secdata-0.0.2.3.dist-info/top_level.txt
secdata-0.0.2.3.dist-info/RECORD
