Metadata-Version: 2.1
Name: secdata
Version: 0.0.2.3
Summary: Easily Download Financial Data reported to SEC
Home-page: https://github.com/voulkon/secdata
Author: Konstantinos Voulgaropoulos
Author-email: voulkon93@gmail.com
License: MIT
Project-URL: Source Code, https://github.com/voulkon/secdata
Keywords: financial,reporting,us-gaap,gaap,sec,api
Platform: UNKNOWN
Classifier: Programming Language :: Python :: 3
Classifier: License :: OSI Approved :: MIT License
Classifier: Operating System :: OS Independent
License-File: LICENSE
